adbblitz/README.md
adbblitz/__init__.py
adbblitz/requirements.txt
adbblitz/scrcpy-server.jar
adbblitz/thirdparty.json
adbblitz-0.10.dist-info/LICENSE.rst
adbblitz-0.10.dist-info/METADATA
adbblitz-0.10.dist-info/WHEEL
adbblitz-0.10.dist-info/top_level.txt
adbblitz-0.10.dist-info/RECORD
