Metadata-Version: 2.1
Name: adbblitz
Version: 0.10
Summary: ADB - The fastest screenshots - scrcpy stream directly to NumPy (without scrcpy.exe) - no root required!
Home-page: https://github.com/hansalemaos/adbblitz
Author: Johannes Fischer
Author-email: aulasparticularesdealemaosp@gmail.com
License: MIT
Keywords: port,tcp,usb,adb,screencap,screenshots,fast,Android
Classifier: Development Status :: 4 - Beta
Classifier: Programming Language :: Python :: 3 :: Only
Classifier: Programming Language :: Python :: 3.10
Classifier: Topic :: Software Development :: Libraries :: Python Modules
Classifier: Topic :: Utilities
License-File: LICENSE.rst
Requires-Dist: adbutils
Requires-Dist: av
Requires-Dist: get-free-port
Requires-Dist: kthread
Requires-Dist: kthread-sleep
Requires-Dist: numpy
Requires-Dist: subprocesskiller
